neuron_bci_schemas/__init__.py
neuron_bci_schemas/config.py
neuron_bci_schemas/enum_types.py
neuron_bci_schemas/input.py
neuron_bci_schemas/model_process.py
neuron_bci_schemas/result.py
neuron_bci_schemas/train.py
neuron_bci_schemas-0.7.0.dist-info/METADATA
neuron_bci_schemas-0.7.0.dist-info/WHEEL
neuron_bci_schemas-0.7.0.dist-info/RECORD
