Metadata-Version: 2.1
Name: neuron-bci-schemas
Version: 0.7.0
Summary: 
Author: Никита Есипов
Author-email: dasaderto@gmail.com
Requires-Python: >=3.10,<4.0
Classifier: Programming Language :: Python :: 3
Classifier: Programming Language :: Python :: 3.10
Classifier: Programming Language :: Python :: 3.11
Classifier: Programming Language :: Python :: 3.12
Requires-Dist: datasets (>=2.16.1,<3.0.0)
Requires-Dist: jsonlines (>=4.0.0,<5.0.0)
Requires-Dist: pandas (>=2.2.0,<3.0.0)
Requires-Dist: pydantic (>=2.5.3,<3.0.0)
Requires-Dist: scikit-learn (>=1.4.0,<2.0.0)
Requires-Dist: torch (>=2.1.0,<3.0.0)
Requires-Dist: transformers (>=4.27.4,<5.0.0)
Requires-Dist: trl (>=0.6,<0.7)
